algn2pheno/__init__.py
algn2pheno/__main__.py
algn2pheno/a2p_classes.py
algn2pheno/arg_input.py
algn2pheno/requirements.txt
algn2pheno-1.1.5.dist-info/entry_points.txt
algn2pheno-1.1.5.dist-info/LICENSE
algn2pheno-1.1.5.dist-info/WHEEL
algn2pheno-1.1.5.dist-info/METADATA
algn2pheno-1.1.5.dist-info/RECORD
