Metadata-Version: 2.1
Name: algn2pheno
Version: 1.1.5
Summary: A bioinformatics tool for rapid screening of genetic features (nt or aa changes) potentially linked to specific phenotypes
Home-page: https://github.com/SantosJGND/algn2pheno
License: MIT
Author: SantosJGND
Author-email: dourado.jns@gmail.com
Requires-Python: >=3.8,<4.0
Classifier: License :: OSI Approved :: MIT License
Classifier: Programming Language :: Python :: 3
Classifier: Programming Language :: Python :: 3.10
Classifier: Programming Language :: Python :: 3.8
Classifier: Programming Language :: Python :: 3.9
Requires-Dist: biopython (>=1.79,<2.0)
Requires-Dist: numpy (>=1.3,<2.0)
Requires-Dist: pandas (>=1.3.5,<2.0.0)
Requires-Dist: sqlalchemy (>=1.4.4,<2.0.0)
Project-URL: Repository, https://github.com/SantosJGND/algn2pheno
